{
  "id": "mondsturz",
  "title": "Mondsturz",
  "description": "Mondsturz System für FoundryVTT",
  "version": "1.3.6",
  "compatibility": {
    "minimum": 10,
    "verified": "11.299",
    "maximum": 11
  },
  "authors": [
    {
      "name": "Grisu",
      "dicscord": "Grisu#9889"
    }
  ],
  "esmodules": [
    "module/mondsturz.mjs"
  ],
  "styles": [
    "css/mondsturz.css"
  ],
  "packs": [
    {
      "label": "MS RollTables",
      "type": "RollTable",
      "name": "ms-rolltable",
      "path": "packs/ms-rolltables.db",
      "system": "mondsturz"
    },
    {
      "label": "MS Merkmale",
      "type": "Item",
      "name": "ms-merkmale",
      "path": "packs/ms-merkmale.db",
      "system": "mondsturz"
    },
    {
      "label": "MS Regelwerk",
      "type": "JournalEntry",
      "name": "ms-regelwerk",
      "path": "packs/ms-regelwerk.db",
      "system": "mondsturz"
    }
    ,
    {
      "label": "MS Macros",
      "type": "Macro",
      "name": "ms-macros",
      "path": "packs/ms-macros.db",
      "system": "mondsturz"
    }
  ],
  "gridDistance": 1,
  "gridUnits": "m",
  "url": "",
  "manifest": "https://raw.githubusercontent.com/Grisu98/mondsturz/main/system.json",
  "download": "https://github.com/Grisu98/mondsturz/archive/refs/tags/V1.3.6.zip",
  "changelog": "CHANGELOG.md"
}