{
  "Actor": {
    "types": [
      "character",
      "npc"
    ],
    "templates": {
      "common": {
        "talentGruppen": {
          "handwerk": {
            "wert": 1,
            "mod": 0,
            "invested": 0,
            "maxTalent": 0,
            "label": "Handwerk"
          },
          "wissen": {
            "wert": 1,
            "mod": 0,
            "invested": 0,
            "maxTalent": 0,
            "label": "Wissen"
          },
          "wildnisleben": {
            "wert": 1,
            "mod": 0,
            "invested": 0,
            "maxTalent": 0,
            "label": "Wildnisleben"
          },
          "kunst": {
            "wert": 1,
            "mod": 0,
            "invested": 0,
            "maxTalent": 0,
            "label": "Kunst"
          },
          "naturwissenschaften": {
            "wert": 1,
            "mod": 0,
            "invested": 0,
            "maxTalent": 0,
            "label": "Naturwissenschaften"
          },
          "soziale": {
            "wert": 1,
            "mod": 0,
            "invested": 0,
            "maxTalent": 0,
            "label": "Soziale Künste"
          },
          "zwielichtiges": {
            "wert": 1,
            "mod": 0,
            "invested": 0,
            "maxTalent": 0,
            "label": "Zwielichtiges"
          },
          "koerper": {
            "wert": 1,
            "mod": 0,
            "invested": 0,
            "maxTalent": 0,
            "label": "Körper"
          },
          "fortbewegung": {
            "wert": 1,
            "mod": 0,
            "invested": 0,
            "maxTalent": 0,
            "label": "Fortbewegung"
          },
          "nahkampf": {
            "wert": 1,
            "mod": 0,
            "invested": 0,
            "maxTalent": 0,
            "label": "Nahkampf"
          },
          "fernkampf": {
            "wert": 1,
            "mod": 0,
            "invested": 0,
            "maxTalent": 0,
            "label": "Fernkampf"
          },
          "mysthkuenste": {
            "wert": 0,
            "mod": 0,
            "invested": 0,
            "maxTalent": 0,
            "label": "Mysthkünste"
          },
          "magieschulen": {
            "wert": 0,
            "mod": 0,
            "invested": 0,
            "maxTalent": 0,
            "label": "Magieschulen"
          },
          "diverse1": {
            "wert": 0,
            "mod": 0,
            "invested": 0,
            "maxTalent": 0,
            "label": "Diverse Talente I"
          },
          "diverse2": {
            "wert": 0,
            "mod": 0,
            "invested": 0,
            "maxTalent": 0,
            "label": "Diverse Talente II"
          }
        },
        "talente": {
          "bauen": {
            "wert": 0,
            "talentKey": "handwerk",
            "mod": 0,
            "istHobby": false,
            "istBeruf": false,
            "label": "Bauen"
          },
          "hacken": {
            "wert": 0,
            "talentKey": "handwerk",
            "mod": 0,
            "istHobby": false,
            "istBeruf": false,
            "label": "Hacken"
          },
          "heilkunst": {
            "wert": 0,
            "talentKey": "handwerk",
            "mod": 0,
            "istHobby": false,
            "istBeruf": false,
            "label": "Heilkunst"
          },
          "ingenieurwesen": {
            "wert": 0,
            "talentKey": "handwerk",
            "mod": 0,
            "istHobby": false,
            "istBeruf": false,
            "label": "Ingenieurwesen"
          },
          "kochen": {
            "wert": 0,
            "talentKey": "handwerk",
            "mod": 0,
            "istHobby": false,
            "istBeruf": false,
            "label": "Kochen"
          },
          "reperatur": {
            "wert": 0,
            "talentKey": "handwerk",
            "mod": 0,
            "istHobby": false,
            "istBeruf": false,
            "label": "Reperatur"
          },
          "sprachen": {
            "wert": 0,
            "talentKey": "wissen",
            "mod": 0,
            "istHobby": false,
            "istBeruf": false,
            "label": "Sprachen"
          },
          "trivia": {
            "wert": 0,
            "talentKey": "wissen",
            "mod": 0,
            "istHobby": false,
            "istBeruf": false,
            "label": "Trivia"
          },
          "geschichte": {
            "wert": 0,
            "talentKey": "wissen",
            "mod": 0,
            "istHobby": false,
            "istBeruf": false,
            "label": "Geschichte"
          },
          "kriegskunst": {
            "wert": 0,
            "talentKey": "wissen",
            "mod": 0,
            "istHobby": false,
            "istBeruf": false,
            "label": "Kriegskunst"
          },
          "religion": {
            "wert": 0,
            "talentKey": "wissen",
            "mod": 0,
            "istHobby": false,
            "istBeruf": false,
            "label": "Relegion"
          },
          "waffenkunde": {
            "wert": 0,
            "talentKey": "wissen",
            "mod": 0,
            "istHobby": false,
            "istBeruf": false,
            "label": "Waffenkunde"
          },
          "fallenstellen": {
            "wert": 0,
            "talentKey": "wildnisleben",
            "mod": 0,
            "istHobby": false,
            "istBeruf": false,
            "label": "Fallen stellen"
          },
          "fischerei": {
            "wert": 0,
            "talentKey": "wildnisleben",
            "mod": 0,
            "istHobby": false,
            "istBeruf": false,
            "label": "Fischerei"
          },
          "lager": {
            "wert": 0,
            "talentKey": "wildnisleben",
            "mod": 0,
            "istHobby": false,
            "istBeruf": false,
            "label": "Lager bauen"
          },
          "orientierung": {
            "wert": 0,
            "talentKey": "wildnisleben",
            "mod": 0,
            "istHobby": false,
            "istBeruf": false,
            "label": "Orientierung"
          },
          "spurenlesen": {
            "wert": 0,
            "talentKey": "wildnisleben",
            "mod": 0,
            "istHobby": false,
            "istBeruf": false,
            "label": "Spurenlesen"
          },
          "zaehmen": {
            "wert": 0,
            "talentKey": "wildnisleben",
            "mod": 0,
            "istHobby": false,
            "istBeruf": false,
            "label": "Zähmen"
          },
          "astrologie": {
            "wert": 0,
            "talentKey": "naturwissenschaften",
            "mod": 0,
            "istHobby": false,
            "istBeruf": false,
            "label": "Astrologie"
          },
          "geowissenschaften": {
            "wert": 0,
            "talentKey": "naturwissenschaften",
            "mod": 0,
            "istHobby": false,
            "istBeruf": false,
            "label": "Geowissenschaften"
          },
          "biologie": {
            "wert": 0,
            "talentKey": "naturwissenschaften",
            "mod": 0,
            "istHobby": false,
            "istBeruf": false,
            "label": "Biologie und Pharmazie"
          },
          "chemie": {
            "wert": 0,
            "talentKey": "naturwissenschaften",
            "mod": 0,
            "istHobby": false,
            "istBeruf": false,
            "label": "Chemie"
          },
          "mathe": {
            "wert": 0,
            "talentKey": "naturwissenschaften",
            "mod": 0,
            "istHobby": false,
            "istBeruf": false,
            "label": "Mathe und Physik"
          },
          "mythstaub": {
            "wert": 0,
            "talentKey": "naturwissenschaften",
            "mod": 0,
            "istHobby": false,
            "istBeruf": false,
            "label": "Mythstaub"
          },
          "beruhigen": {
            "wert": 0,
            "talentKey": "soziale",
            "mod": 0,
            "istHobby": false,
            "istBeruf": false,
            "label": "Beruhigen und Ansporen"
          },
          "betoeren": {
            "wert": 0,
            "talentKey": "soziale",
            "mod": 0,
            "istHobby": false,
            "istBeruf": false,
            "label": "Betören"
          },
          "betteln": {
            "wert": 0,
            "talentKey": "soziale",
            "mod": 0,
            "istHobby": false,
            "istBeruf": false,
            "label": "Betteln und Mitleid erzeugen"
          },
          "feilschen": {
            "wert": 0,
            "talentKey": "soziale",
            "mod": 0,
            "istHobby": false,
            "istBeruf": false,
            "label": "Feilschen"
          },
          "luegen": {
            "wert": 0,
            "talentKey": "soziale",
            "mod": 0,
            "istHobby": false,
            "istBeruf": false,
            "label": "Lügen"
          },
          "ueberreden": {
            "wert": 0,
            "talentKey": "soziale",
            "mod": 0,
            "istHobby": false,
            "istBeruf": false,
            "label": "Überreden"
          },
          "recherche": {
            "wert": 0,
            "talentKey": "zwielichtiges",
            "mod": 0,
            "istHobby": false,
            "istBeruf": false,
            "label": "Recherche"
          },
          "diebeskunst": {
            "wert": 0,
            "talentKey": "zwielichtiges",
            "mod": 0,
            "istHobby": false,
            "istBeruf": false,
            "label": "Diebeskunst"
          },
          "fesseln": {
            "wert": 0,
            "talentKey": "zwielichtiges",
            "mod": 0,
            "istHobby": false,
            "istBeruf": false,
            "label": "Fesseln"
          },
          "gassenwissen": {
            "wert": 0,
            "talentKey": "zwielichtiges",
            "mod": 0,
            "istHobby": false,
            "istBeruf": false,
            "label": "Gassenwissen"
          },
          "gesellschaftsspiele": {
            "wert": 0,
            "talentKey": "zwielichtiges",
            "mod": 0,
            "istHobby": false,
            "istBeruf": false,
            "label": "Gesellschaftsspiele"
          },
          "verbergen": {
            "wert": 0,
            "talentKey": "zwielichtiges",
            "mod": 0,
            "istHobby": false,
            "istBeruf": false,
            "label": "Verbergen"
          },
          "akrobatik": {
            "wert": 0,
            "talentKey": "koerper",
            "mod": 0,
            "istHobby": false,
            "istBeruf": false,
            "label": "Akrobatik"
          },
          "klettern": {
            "wert": 0,
            "talentKey": "koerper",
            "mod": 0,
            "istHobby": false,
            "istBeruf": false,
            "label": "Klettern"
          },
          "kraftakt": {
            "wert": 0,
            "talentKey": "koerper",
            "mod": 0,
            "istHobby": false,
            "istBeruf": false,
            "label": "Kraftakt"
          },
          "laufen": {
            "wert": 0,
            "talentKey": "koerper",
            "mod": 0,
            "istHobby": false,
            "istBeruf": false,
            "label": "Laufen"
          },
          "schwimmen": {
            "wert": 0,
            "talentKey": "koerper",
            "mod": 0,
            "istHobby": false,
            "istBeruf": false,
            "label": "Schwimmen"
          },
          "sinnesschaerfe": {
            "wert": 0,
            "talentKey": "koerper",
            "mod": 0,
            "istHobby": false,
            "istBeruf": false,
            "label": "Sinnesschärfe"
          },
          "dronen": {
            "wert": 0,
            "talentKey": "fortbewegung",
            "mod": 0,
            "istHobby": false,
            "istBeruf": false,
            "label": "Dronen"
          },
          "einspurige": {
            "wert": 0,
            "talentKey": "fortbewegung",
            "mod": 0,
            "istHobby": false,
            "istBeruf": false,
            "label": "Einspurige"
          },
          "luftfahrt": {
            "wert": 0,
            "talentKey": "fortbewegung",
            "mod": 0,
            "istHobby": false,
            "istBeruf": false,
            "label": "Luftfahrt"
          },
          "reiten": {
            "wert": 0,
            "talentKey": "fortbewegung",
            "mod": 0,
            "istHobby": false,
            "istBeruf": false,
            "label": "Reiten"
          },
          "schiffsfahrt": {
            "wert": 0,
            "talentKey": "fortbewegung",
            "mod": 0,
            "istHobby": false,
            "istBeruf": false,
            "label": "Schiffsfahrt"
          },
          "zweispurig": {
            "wert": 0,
            "talentKey": "fortbewegung",
            "mod": 0,
            "istHobby": false,
            "istBeruf": false,
            "label": "Zweispurig"
          },
          "nahexoten": {
            "wert": 0,
            "talentKey": "nahkampf",
            "mod": 0,
            "istHobby": false,
            "istBeruf": false,
            "label": "Exoten",
            "dmgMod": 0
          },
          "faustkampf": {
            "wert": 0,
            "talentKey": "nahkampf",
            "mod": 0,
            "istHobby": false,
            "istBeruf": false,
            "label": "Faustkampf",
            "dmgMod": 0
          },
          "klingenwaffen": {
            "wert": 0,
            "talentKey": "nahkampf",
            "mod": 0,
            "istHobby": false,
            "istBeruf": false,
            "label": "Klingenwaffen",
            "dmgMod": 0
          },
          "schildkunst": {
            "wert": 0,
            "talentKey": "nahkampf",
            "mod": 0,
            "istHobby": false,
            "istBeruf": false,
            "label": "Schildkunst",
            "dmgMod": 0
          },
          "stangenwaffen": {
            "wert": 0,
            "talentKey": "nahkampf",
            "mod": 0,
            "istHobby": false,
            "istBeruf": false,
            "label": "Stangenwaffen",
            "dmgMod": 0
          },
          "wuchtwaffen": {
            "wert": 0,
            "talentKey": "nahkampf",
            "mod": 0,
            "istHobby": false,
            "istBeruf": false,
            "label": "Wuchtwaffen",
            "dmgMod": 0
          },
          "bogenwaffen": {
            "wert": 0,
            "talentKey": "fernkampf",
            "mod": 0,
            "istHobby": false,
            "istBeruf": false,
            "label": "Bogenwaffen",
            "dmgMod": 0
          },
          "fernexoten": {
            "wert": 0,
            "talentKey": "fernkampf",
            "mod": 0,
            "istHobby": false,
            "istBeruf": false,
            "label": "Exoten",
            "dmgMod": 0
          },
          "kurzwaffen": {
            "wert": 0,
            "talentKey": "fernkampf",
            "mod": 0,
            "istHobby": false,
            "istBeruf": false,
            "label": "Kurzwaffen",
            "dmgMod": 0
          },
          "langwaffen": {
            "wert": 0,
            "talentKey": "fernkampf",
            "mod": 0,
            "istHobby": false,
            "istBeruf": false,
            "label": "Langwaffen",
            "dmgMod": 0
          },
          "schweres": {
            "wert": 0,
            "talentKey": "fernkampf",
            "mod": 0,
            "istHobby": false,
            "istBeruf": false,
            "label": "Schweres Gerät",
            "dmgMod": 0
          },
          "wurfwaffen": {
            "wert": 0,
            "talentKey": "fernkampf",
            "mod": 0,
            "istHobby": false,
            "istBeruf": false,
            "label": "Wurfwaffen",
            "dmgMod": 0
          },
          "ausruf": {
            "wert": 0,
            "talentKey": "mysthkuenste",
            "mod": 0,
            "istHobby": false,
            "istBeruf": false,
            "label": "Ausruf"
          },
          "katalysator": {
            "wert": 0,
            "talentKey": "mysthkuenste",
            "mod": 0,
            "istHobby": false,
            "istBeruf": false,
            "label": "Katalysator"
          },
          "fingerzeichen": {
            "wert": 0,
            "talentKey": "mysthkuenste",
            "mod": 0,
            "istHobby": false,
            "istBeruf": false,
            "label": "Fingerzeichen"
          },
          "runenschrift": {
            "wert": 0,
            "talentKey": "mysthkuenste",
            "mod": 0,
            "istHobby": false,
            "istBeruf": false,
            "label": "Runenschrift"
          },
          "ritual": {
            "wert": 0,
            "talentKey": "mysthkuenste",
            "mod": 0,
            "istHobby": false,
            "istBeruf": false,
            "label": "Ritual"
          },
          "mengatis": {
            "wert": 0,
            "talentKey": "magieschulen",
            "mod": 0,
            "istHobby": false,
            "istBeruf": false,
            "label": "Mengatis"
          },
          "mengatis2": {
            "wert": 0,
            "talentKey": "magieschulen",
            "mod": 0,
            "istHobby": false,
            "istBeruf": false,
            "label": "Mengatis2"
          },
          "arcadus": {
            "wert": 0,
            "talentKey": "magieschulen",
            "mod": 0,
            "istHobby": false,
            "istBeruf": false,
            "label": "Arcadus"
          },
          "persopec": {
            "wert": 0,
            "talentKey": "magieschulen",
            "mod": 0,
            "istHobby": false,
            "istBeruf": false,
            "label": "Persopec"
          },
          "teldora": {
            "wert": 0,
            "talentKey": "magieschulen",
            "mod": 0,
            "istHobby": false,
            "istBeruf": false,
            "label": "Teldora"
          },
          "eigna": {
            "wert": 0,
            "talentKey": "magieschulen",
            "mod": 0,
            "istHobby": false,
            "istBeruf": false,
            "label": "Eigna"
          },
          "aurores": {
            "wert": 0,
            "talentKey": "magieschulen",
            "mod": 0,
            "istHobby": false,
            "istBeruf": false,
            "label": "Aurores"
          },
          "avalon": {
            "wert": 0,
            "talentKey": "magieschulen",
            "mod": 0,
            "istHobby": false,
            "istBeruf": false,
            "label": "Avalon"
          },
          "bildende": {
            "wert": 0,
            "talentKey": "kunst",
            "mod": 0,
            "istHobby": false,
            "istBeruf": false,
            "label": "Bildende Künste"
          },
          "singen": {
            "wert": 0,
            "talentKey": "kunst",
            "mod": 0,
            "istHobby": false,
            "istBeruf": false,
            "label": "Singen"
          },
          "instrumente": {
            "wert": 0,
            "talentKey": "kunst",
            "mod": 0,
            "istHobby": false,
            "istBeruf": false,
            "label": "Instrumente"
          },
          "literatur": {
            "wert": 0,
            "talentKey": "kunst",
            "mod": 0,
            "istHobby": false,
            "istBeruf": false,
            "label": "Literatur"
          },
          "darstellende": {
            "wert": 0,
            "talentKey": "kunst",
            "mod": 0,
            "istHobby": false,
            "istBeruf": false,
            "label": "darstellende Künste"
          },
          "verkleiden": {
            "wert": 0,
            "talentKey": "kunst",
            "mod": 0,
            "istHobby": false,
            "istBeruf": false,
            "label": "Verkleiden"
          }
        },
        "attribute": {
          "resistenzen": {
            "immunsystem": {
              "wert": 0,
              "max": 0,
              "mod": 0,
              "label": "Immunsystem"
            },
            "elementar": {
              "wert": 0,
              "max": 0,
              "mod": 0,
              "label": "Elementar"
            },
            "charaktestaerke": {
              "wert": 0,
              "max": 0,
              "mod": 0,
              "label": "Charakterstärke"
            },
            "schmerz": {
              "wert": 0,
              "max": 0,
              "mod": 0,
              "label": "Schmerzen"
            },
            "segen": {
              "wert": 0,
              "max": 0,
              "mod": 0,
              "label": "Segen"
            }
          },
          "koerper": {
            "psyche": {
              "wert": 1,
              "max": 1,
              "mod": 0,
              "label": "Psyche"
            },
            "regeneration": {
              "wert": 1,
              "max": 1,
              "mod": 0,
              "label": "Regeneration"
            },
            "adrenalin": {
              "wert": 1,
              "max": 1,
              "mod": 0,
              "label": "Adrenalin"
            },
            "hyperarmor": {
              "wert": 0,
              "min": 0,
              "max": 0,
              "label": "Hyperarmor"
            },
            "physis": {
              "wert": 1,
              "min": 0,
              "max": 1,
              "label": "Physis"
            },
            "reflex": {
              "wert": 7,
              "max": 0,
              "mod": 0,
              "label": "Reflex"
            },
            "leben": {
              "wert": 5,
              "min": 0,
              "max": 5,
              "label": "Leben"
            },
            "mana": {
              "wert": 3,
              "max": 3,
              "mod": 0,
              "label": "Mana"
            },
            "ruestwert": {
              "wert": 0,
              "max": 0,
              "mod": 0,
              "label": "Rüstzustand"
            }
          },
          "ruestwert": {
            "stich": {
              "wert": 0,
              "max": 0,
              "mod": 0,
              "label": "Stich"
            },
            "schnitt": {
              "wert": 0,
              "max": 0,
              "mod": 0,
              "label": "Schnitt"
            },
            "stumpf": {
              "wert": 0,
              "max": 0,
              "mod": 0,
              "label": "Stumpf"
            },
            "energie": {
              "wert": 0,
              "max": 0,
              "mod": 0,
              "label": "Energie"
            }
          }
        },
        "magie": {
          "mysthkuenste": {
            "wert": 0,
            "mod": 0,
            "label": "Mysthkünste",
            "talente": {
              "ausruf": {
                "wert": 0,
                "talentKey": "mysthkuenste",
                "mod": 0,
                "istHobby": false,
                "istBeruf": false,
                "label": "Ausruf"
              },
              "katalysator": {
                "wert": 0,
                "talentKey": "mysthkuenste",
                "mod": 0,
                "istHobby": false,
                "istBeruf": false,
                "label": "Katalysator"
              },
              "fingerzeichen": {
                "wert": 0,
                "talentKey": "mysthkuenste",
                "mod": 0,
                "istHobby": false,
                "istBeruf": false,
                "label": "Fingerzeichen"
              },
              "runenschrift": {
                "wert": 0,
                "talentKey": "mysthkuenste",
                "mod": 0,
                "istHobby": false,
                "istBeruf": false,
                "label": "Runenschrift"
              },
              "ritual": {
                "wert": 0,
                "talentKey": "mysthkuenste",
                "mod": 0,
                "istHobby": false,
                "istBeruf": false,
                "label": "Ritual"
              }
            }
          },
          "magieschulen": {
            "wert": 0,
            "mod": 0,
            "label": "Magieschulen",
            "talente": {
              "mengatis": {
                "wert": 0,
                "talentKey": "magieschulen",
                "mod": 0,
                "istHobby": false,
                "istBeruf": false,
                "label": "Mengatis"
              },
              "mengatis2": {
                "wert": 0,
                "talentKey": "magieschulen",
                "mod": 0,
                "istHobby": false,
                "istBeruf": false,
                "label": "Mengatis2"
              },
              "arcadus": {
                "wert": 0,
                "talentKey": "magieschulen",
                "mod": 0,
                "istHobby": false,
                "istBeruf": false,
                "label": "Arcadus"
              },
              "persopec": {
                "wert": 0,
                "talentKey": "magieschulen",
                "mod": 0,
                "istHobby": false,
                "istBeruf": false,
                "label": "Persopec"
              },
              "teldora": {
                "wert": 0,
                "talentKey": "magieschulen",
                "mod": 0,
                "istHobby": false,
                "istBeruf": false,
                "label": "Teldora"
              },
              "eigna": {
                "wert": 0,
                "talentKey": "magieschulen",
                "mod": 0,
                "istHobby": false,
                "istBeruf": false,
                "label": "Eigna"
              },
              "aurores": {
                "wert": 0,
                "talentKey": "magieschulen",
                "mod": 0,
                "istHobby": false,
                "istBeruf": false,
                "label": "Aurores"
              },
              "avalon": {
                "wert": 0,
                "talentKey": "magieschulen",
                "mod": 0,
                "istHobby": false,
                "istBeruf": false,
                "label": "Avalon"
              }
            }
          }
        },
        "misc": {
          "advSetting": false,
          "compact": true,
          "xp": 0,
          "rang": 0,
          "inventar": {
            "wert": 0,
            "max": 10,
            "mod": 0
          },
          "notizen": {
            "wert": "",
            "label": "Notizen"
          },
          "adrenalin": {},
          "gold": 0
        },
        "details": {
          "spitzname": {
            "wert": "",
            "label": "Spitzname"
          },
          "alter": {
            "wert": "",
            "label": "Alter"
          },
          "konstellation": {
            "wert": "",
            "label": "Konstellation"
          },
          "geschlecht": {
            "wert": "",
            "label": "Geschlecht"
          },
          "groesse": {
            "wert": "",
            "label": "Größe"
          },
          "gewicht": {
            "wert": "",
            "label": "Gewicht"
          },
          "volk": {
            "wert": "",
            "label": "Volk"
          },
          "beruf": {
            "wert": "",
            "label": "Beruf"
          },
          "hobby": {
            "wert": "",
            "label": "Hobby"
          },
          "nahtoterfharung": {
            "wert": "",
            "label": "Nahtoterfahrung"
          },
          "inbrunst": {
            "wert": "",
            "label": "Inbrunst der Seele"
          },
          "familienstand": {
            "wert": "",
            "label": "Familienstand"
          }
        }
      },
      "tGruppen": {
        "talentGruppen": {
          "handwerk": {
            "wert": 1,
            "mod": 0,
            "invested": 0,
            "maxTalent": 0,
            "label": "Handwerk"
          },
          "wissen": {
            "wert": 1,
            "mod": 0,
            "invested": 0,
            "maxTalent": 0,
            "label": "Wissen"
          },
          "wildnisleben": {
            "wert": 1,
            "mod": 0,
            "invested": 0,
            "maxTalent": 0,
            "label": "Wildnisleben"
          },
          "kunst": {
            "wert": 1,
            "mod": 0,
            "invested": 0,
            "maxTalent": 0,
            "label": "Kunst"
          },
          "naturwissenschaften": {
            "wert": 1,
            "mod": 0,
            "invested": 0,
            "maxTalent": 0,
            "label": "Naturwissenschaften"
          },
          "soziale": {
            "wert": 1,
            "mod": 0,
            "invested": 0,
            "maxTalent": 0,
            "label": "Soziale Künste"
          },
          "zwielichtiges": {
            "wert": 1,
            "mod": 0,
            "invested": 0,
            "maxTalent": 0,
            "label": "Zwielichtiges"
          },
          "koerper": {
            "wert": 1,
            "mod": 0,
            "invested": 0,
            "maxTalent": 0,
            "label": "Körper"
          },
          "fortbewegung": {
            "wert": 1,
            "mod": 0,
            "invested": 0,
            "maxTalent": 0,
            "label": "Fortbewegung"
          },
          "nahkampf": {
            "wert": 1,
            "mod": 0,
            "invested": 0,
            "maxTalent": 0,
            "label": "Nahkampf"
          },
          "fernkampf": {
            "wert": 1,
            "mod": 0,
            "invested": 0,
            "maxTalent": 0,
            "label": "Fernkampf"
          },
          "mysthkuenste": {
            "wert": 0,
            "mod": 0,
            "invested": 0,
            "maxTalent": 0,
            "label": "Mysthkünste"
          },
          "magieschulen": {
            "wert": 0,
            "mod": 0,
            "invested": 0,
            "maxTalent": 0,
            "label": "Magieschulen"
          },
          "diverse1": {
            "wert": 0,
            "mod": 0,
            "invested": 0,
            "maxTalent": 0,
            "label": "Diverse Talente I"
          },
          "diverse2": {
            "wert": 0,
            "mod": 0,
            "invested": 0,
            "maxTalent": 0,
            "label": "Diverse Talente II"
          }
        }
      },
      "attr": {
        "resistenzen": {
          "immunsystem": {
            "wert": 0,
            "max": 0,
            "mod": 0,
            "label": "Immunsystem"
          },
          "elementar": {
            "wert": 0,
            "max": 0,
            "mod": 0,
            "label": "Elementar"
          },
          "charaktestaerke": {
            "wert": 0,
            "max": 0,
            "mod": 0,
            "label": "Charakterstärke"
          },
          "schmerz": {
            "wert": 0,
            "max": 0,
            "mod": 0,
            "label": "Schmerzen"
          },
          "segen": {
            "wert": 0,
            "max": 0,
            "mod": 0,
            "label": "Segen"
          }
        },
        "koerper": {
          "psyche": {
            "wert": 1,
            "max": 1,
            "mod": 0,
            "label": "Psyche"
          },
          "regeneration": {
            "wert": 1,
            "max": 1,
            "mod": 0,
            "label": "Regeneration"
          },
          "adrenalin": {
            "wert": 1,
            "max": 1,
            "mod": 0,
            "label": "Adrenalin"
          },
          "hyperarmor": {
            "wert": 0,
            "min": 0,
            "max": 0,
            "label": "Hyperarmor"
          },
          "physis": {
            "wert": 1,
            "min": 0,
            "max": 1,
            "label": "Physis"
          },
          "reflex": {
            "wert": 7,
            "max": 0,
            "mod": 0,
            "label": "Reflex"
          },
          "leben": {
            "wert": 5,
            "min": 0,
            "max": 5,
            "label": "Leben"
          },
          "mana": {
            "wert": 3,
            "max": 3,
            "mod": 0,
            "label": "Mana"
          },
          "ruestwert": {
            "wert": 0,
            "max": 0,
            "mod": 0,
            "label": "Rüstwert"
          }
        },
        "ruestwert": {
          "stich": {
            "wert": 0,
            "max": 0,
            "mod": 0,
            "label": "Stich"
          },
          "schnitt": {
            "wert": 0,
            "max": 0,
            "mod": 0,
            "label": "Schnitt"
          },
          "stumpf": {
            "wert": 0,
            "max": 0,
            "mod": 0,
            "label": "Stumpf"
          },
          "energie": {
            "wert": 0,
            "max": 0,
            "mod": 0,
            "label": "Energie"
          }
        }
      }
    },
    "character": {
      "templates": [
        "common"
      ]
    },
    "npc": {
      "templates": [
        "common"
      ]
    }
  },
  "Item": {
    "types": [
      "waffe",
      "zauber",
      "gegenstand",
      "merkmal"
    ],
    "templates": {
      "baseItem": {
        "weight": 0,
        "description": ""
      }
    },
    "zauber": {
      "weight": 0,
      "description": "",
      "level": {
        "level0": {
          "formula": "",
          "text": "",
          "mana": 0,
          "label": "Trick"
        },
        "level1": {
          "formula": "",
          "text": "",
          "mana": 0,
          "label": "Stufe Eins"
        },
        "level2": {
          "formula": "",
          "text": "",
          "mana": 0,
          "label": "Stufe Zwei"
        },
        "level3": {
          "formula": "",
          "text": "",
          "mana": 0,
          "label": "Stufe Drei"
        },
        "level4": {
          "formula": "",
          "text": "",
          "mana": 0,
          "label": "Stufe Vier"
        },
        "level5": {
          "formula": "",
          "text": "",
          "mana": 0,
          "label": "Stufe Fünf"
        }
      },
      "stats": {
        "talentKey": "",
        "quality": 2,
        "tags": [],
        "level": 0,
        "skillKey": ""
      },
      "compact": true,
      "value": 0,
      "tags": ""
    },
    "gegenstand": {
      "description": "",
      "weight": 1,
      "compact": true,
      "value": 0,
      "quantity": 1
    },
    "waffe": {
      "weight": 1,
      "stats": {
        "talentKey": "",
        "quality": 2,
        "element": "",
        "chance": "",
        "damage": "",
        "crit": "",
        "boni": "",
        "tags": [],
        "level": 0,
        "skillKey": "",
        "ep": 0
      },
      "description": "",
      "compact": true,
      "value": 0,
      "tags": [],
      "quantity": 1
    },
    "merkmal": {
      "type": "eigenschaft",
      "rank": 0,
      "ranks": {
        "0": "",
        "1": "",
        "2": "",
        "3": "",
        "4": ""
      },
      "description": ""
    }
  }
}